crispy_forms/LICENSE
crispy_forms/__init__.py
crispy_forms/base.py
crispy_forms/bootstrap.py
crispy_forms/exceptions.py
crispy_forms/helper.py
crispy_forms/layout.py
crispy_forms/layout_slice.py
crispy_forms/utils.py
crispy_forms/templatetags/__init__.py
crispy_forms/templatetags/crispy_forms_field.py
crispy_forms/templatetags/crispy_forms_filters.py
crispy_forms/templatetags/crispy_forms_tags.py
crispy_forms/templatetags/crispy_forms_utils.py
django_crispy_forms-2.3.dist-info/LICENSE.txt
django_crispy_forms-2.3.dist-info/METADATA
django_crispy_forms-2.3.dist-info/WHEEL
django_crispy_forms-2.3.dist-info/top_level.txt
django_crispy_forms-2.3.dist-info/RECORD
