Metadata-Version: 2.1
Name: django-crispy-forms
Version: 2.3
Summary: Best way to have Django DRY forms
Author-email: Miguel Araujo <miguel.araujo.perez@gmail.com>
License: MIT
Project-URL: Homepage, https://github.com/django-crispy-forms/django-crispy-forms
Project-URL: Issues, https://github.com/django-crispy-forms/django-crispy-forms/issues
Project-URL: Changelog, https://github.com/django-crispy-forms/django-crispy-forms/releases
Keywords: forms,django,crispy,DRY
Classifier: Development Status :: 5 - Production/Stable
Classifier: Environment :: Web Environment
Classifier: Framework :: Django
Classifier: Framework :: Django :: 4.2
Classifier: Framework :: Django :: 5.0
Classifier: Framework :: Django :: 5.1
Classifier: License :: OSI Approved :: MIT License
Classifier: Operating System :: OS Independent
Classifier: Programming Language :: JavaScript
Classifier: Programming Language :: Python :: 3
Classifier: Programming Language :: Python :: 3.8
Classifier: Programming Language :: Python :: 3.9
Classifier: Programming Language :: Python :: 3.10
Classifier: Programming Language :: Python :: 3.11
Classifier: Programming Language :: Python :: 3.12
Classifier: Topic :: Internet :: WWW/HTTP
Classifier: Topic :: Internet :: WWW/HTTP :: Dynamic Content
Classifier: Topic :: Software Development :: Libraries :: Python Modules
Requires-Python: >=3.8
License-File: LICENSE.txt
Requires-Dist: django>=4.2
